{"cameraMode":{"drawMode":0,"name":"Shaded","section":"Shading Mode"},"sceneLighting":true,"audioPlay":false,"sceneViewState":{"showFog":true,"showMaterialUpdate":false,"showSkybox":true,"showFlares":true,"showImageEffects":true,"showParticleSystems":true},"in2DMode":false,"pivot":{"x":498.68206787109377,"y":4.497433185577393,"z":338.98016357421877},"rotation":{"x":-0.055775538086891177,"y":0.47865837812423708,"z":-0.030508069321513177,"w":-0.8758337497711182},"size":11.114920616149903,"orthographic":false}